postman_repl/postman_repl_test.py
postman_repl/postman_repl.py
postman_repl/__init__.py
postman_repl-0.0.1.dist-info/METADATA
postman_repl-0.0.1.dist-info/RECORD
postman_repl-0.0.1.dist-info/WHEEL
postman_repl-0.0.1.dist-info/entry_points.txt
postman_repl-0.0.1.dist-info/metadata.json
postman_repl-0.0.1.dist-info/top_level.txt
postman_repl-0.0.1.dist-info/DESCRIPTION.rst
