Metadata-Version: 2.0
Name: postman-repl
Version: 0.0.1
Summary: A repl providing api access using postman configuration
Home-page: https://github.com/johnnadratowski/postman-repl
Author: John Nadratowski
Author-email: john.nadratowski@gmail.com
License: Apache Software License
Keywords: postman repl read-eval-print api rest
Platform: UNKNOWN
Classifier: Development Status :: 4 - Beta
Classifier: Intended Audience :: Developers
Classifier: Topic :: Software Development :: User Interfaces
Classifier: License :: OSI Approved :: Apache Software License
Classifier: Programming Language :: Python :: 3
Classifier: Programming Language :: Python :: 3.2
Classifier: Programming Language :: Python :: 3.3
Classifier: Programming Language :: Python :: 3.4
Requires-Dist: IPython
Requires-Dist: jinja2
Requires-Dist: argparse
Requires-Dist: requests
